mcp_this/__init__.py
mcp_this/__main__.py
mcp_this/mcp_server.py
mcp_this/prompts.py
mcp_this/tools.py
mcp_this/configs/default.yaml
mcp_this/configs/editing.yaml
mcp_this/configs/github.yaml
mcp_this/templates/tool_description.md.jinja2
iflow_mcp_shane_kercheval_mcp_this-0.0.22.dist-info/METADATA
iflow_mcp_shane_kercheval_mcp_this-0.0.22.dist-info/WHEEL
iflow_mcp_shane_kercheval_mcp_this-0.0.22.dist-info/entry_points.txt
iflow_mcp_shane_kercheval_mcp_this-0.0.22.dist-info/licenses/LICENSE
iflow_mcp_shane_kercheval_mcp_this-0.0.22.dist-info/RECORD
