Metadata-Version: 2.4
Name: iflow-mcp_shane_kercheval_mcp_this
Version: 0.0.22
Summary: MCP Server that exposes CLI commands as tools for Claude using YAML configuration files
Author-email: Shane Kercheval <shane.kercheval@gmail.com>
License-File: LICENSE
Keywords: AI,CLI,Claude,MCP,tools
Classifier: Development Status :: 4 - Beta
Classifier: Intended Audience :: Developers
Classifier: Programming Language :: Python :: 3
Classifier: Programming Language :: Python :: 3.11
Classifier: Topic :: Software Development :: Libraries :: Python Modules
Classifier: Topic :: Utilities
Requires-Python: >=3.11
Requires-Dist: click>=8.1.8
Requires-Dist: jinja2>=3.1.6
Requires-Dist: mcp
Requires-Dist: python-dotenv>=1.0.1
Requires-Dist: pyyaml
